hamadmin/__init__.py
hamadmin/django/__init__.py
hamadmin/django/middleware.py
hamadmin/django/settings.py
hamadmin/django/utils.py
hamadmin-0.1.0.dist-info/METADATA
hamadmin-0.1.0.dist-info/WHEEL
hamadmin-0.1.0.dist-info/top_level.txt
hamadmin-0.1.0.dist-info/RECORD
