Metadata-Version: 2.4
Name: hamadmin
Version: 0.1.0
Summary: A collection of utilities and middleware for various frameworks
Author-email: "sahand.esmaeilzadeh" <sahand.esmaeilzadeh@hamravesh.com>
Requires-Python: >=3.8
Requires-Dist: PyJWT>=2.0.0
Requires-Dist: cryptography>=3.0.0
Provides-Extra: django
Requires-Dist: Django>=3.2; extra == "django"
